agent/Agent.py
agent/Chain.py
agent/CleanOutput.py
agent/Config.py
agent/LLM.py
agent/Task.py
agent/Tool.py
agent/Tools/TerminalUse.py
dde_agents-0.0.3.19.dist-info/METADATA
dde_agents-0.0.3.19.dist-info/WHEEL
dde_agents-0.0.3.19.dist-info/top_level.txt
dde_agents-0.0.3.19.dist-info/RECORD
